final_test02/__init__.py
final_test02/adaboost.py
final_test02/grad_boost.py
final_test02/knn.py
final_test02/logistic.py
final_test02/mlp.py
final_test02/perceptron.py
final_test02/random_forest.py
final_test02/sgd.py
final_test02/support_vector.py
final_test02/test.py
final_test02/the.py
final_test02/visualize.py
final_test02/xgboost.py
final_test_02-0.1.0.dist-info/LICENSE
final_test_02-0.1.0.dist-info/METADATA
final_test_02-0.1.0.dist-info/WHEEL
final_test_02-0.1.0.dist-info/top_level.txt
final_test_02-0.1.0.dist-info/RECORD
